setup.py
distributions11/Binomialdistribution.py
distributions11/Gaussiandistribution.py
distributions11/Generaldistribution.py
distributions11/__init__.py
distributions11.egg-info/PKG-INFO
distributions11.egg-info/SOURCES.txt
distributions11.egg-info/dependency_links.txt
distributions11.egg-info/not-zip-safe
distributions11.egg-info/top_level.txt